{
  "version": 1,
  "tenses": ["present", "preterite", "imperfect", "subjunctive_present", "conditional"],
  "persons": ["yo", "tu", "el", "nosotros", "vosotros", "ellos"],
  "verbs": [
    {
      "inf": "ser",
      "tr": "olla (identiteetti)",
      "irr": true,
      "conj": {
        "present": ["soy", "eres", "es", "somos", "sois", "son"],
        "preterite": ["fui", "fuiste", "fue", "fuimos", "fuisteis", "fueron"],
        "imperfect": ["era", "eras", "era", "éramos", "erais", "eran"],
        "subjunctive_present": ["sea", "seas", "sea", "seamos", "seáis", "sean"],
        "conditional": ["sería", "serías", "sería", "seríamos", "seríais", "serían"]
      },
      "imperative": {
        "tu": "sé",
        "usted": "sea",
        "nosotros": "seamos",
        "vosotros": "sed",
        "ustedes": "sean"
      }
    },
    {
      "inf": "estar",
      "tr": "olla (tila/sijainti)",
      "irr": true,
      "conj": {
        "present": ["estoy", "estás", "está", "estamos", "estáis", "están"],
        "preterite": ["estuve", "estuviste", "estuvo", "estuvimos", "estuvisteis", "estuvieron"],
        "imperfect": ["estaba", "estabas", "estaba", "estábamos", "estabais", "estaban"],
        "subjunctive_present": ["esté", "estés", "esté", "estemos", "estéis", "estén"],
        "conditional": ["estaría", "estarías", "estaría", "estaríamos", "estaríais", "estarían"]
      },
      "imperative": {
        "tu": "está",
        "usted": "esté",
        "nosotros": "estemos",
        "vosotros": "estad",
        "ustedes": "estén"
      }
    },
    {
      "inf": "tener",
      "tr": "olla (omistaa)",
      "irr": true,
      "conj": {
        "present": ["tengo", "tienes", "tiene", "tenemos", "tenéis", "tienen"],
        "preterite": ["tuve", "tuviste", "tuvo", "tuvimos", "tuvisteis", "tuvieron"],
        "imperfect": ["tenía", "tenías", "tenía", "teníamos", "teníais", "tenían"],
        "subjunctive_present": ["tenga", "tengas", "tenga", "tengamos", "tengáis", "tengan"],
        "conditional": ["tendría", "tendrías", "tendría", "tendríamos", "tendríais", "tendrían"]
      },
      "imperative": {
        "tu": "ten",
        "usted": "tenga",
        "nosotros": "tengamos",
        "vosotros": "tened",
        "ustedes": "tengan"
      }
    },
    {
      "inf": "haber",
      "tr": "apuverbi",
      "irr": true,
      "conj": {
        "present": ["he", "has", "ha", "hemos", "habéis", "han"],
        "preterite": ["hube", "hubiste", "hubo", "hubimos", "hubisteis", "hubieron"],
        "imperfect": ["había", "habías", "había", "habíamos", "habíais", "habían"],
        "subjunctive_present": ["haya", "hayas", "haya", "hayamos", "hayáis", "hayan"],
        "conditional": ["habría", "habrías", "habría", "habríamos", "habríais", "habrían"]
      },
      "imperative": {
        "tu": "he",
        "usted": "haya",
        "nosotros": "hayamos",
        "vosotros": "habed",
        "ustedes": "hayan"
      }
    },
    {
      "inf": "hacer",
      "tr": "tehdä",
      "irr": true,
      "conj": {
        "present": ["hago", "haces", "hace", "hacemos", "hacéis", "hacen"],
        "preterite": ["hice", "hiciste", "hizo", "hicimos", "hicisteis", "hicieron"],
        "imperfect": ["hacía", "hacías", "hacía", "hacíamos", "hacíais", "hacían"],
        "subjunctive_present": ["haga", "hagas", "haga", "hagamos", "hagáis", "hagan"],
        "conditional": ["haría", "harías", "haría", "haríamos", "haríais", "harían"]
      },
      "imperative": {
        "tu": "haz",
        "usted": "haga",
        "nosotros": "hagamos",
        "vosotros": "haced",
        "ustedes": "hagan"
      }
    },
    {
      "inf": "ir",
      "tr": "mennä",
      "irr": true,
      "conj": {
        "present": ["voy", "vas", "va", "vamos", "vais", "van"],
        "preterite": ["fui", "fuiste", "fue", "fuimos", "fuisteis", "fueron"],
        "imperfect": ["iba", "ibas", "iba", "íbamos", "ibais", "iban"],
        "subjunctive_present": ["vaya", "vayas", "vaya", "vayamos", "vayáis", "vayan"],
        "conditional": ["iría", "irías", "iría", "iríamos", "iríais", "irían"]
      },
      "imperative": {
        "tu": "ve",
        "usted": "vaya",
        "nosotros": "vamos",
        "vosotros": "id",
        "ustedes": "vayan"
      }
    },
    {
      "inf": "poder",
      "tr": "voida",
      "irr": true,
      "conj": {
        "present": ["puedo", "puedes", "puede", "podemos", "podéis", "pueden"],
        "preterite": ["pude", "pudiste", "pudo", "pudimos", "pudisteis", "pudieron"],
        "imperfect": ["podía", "podías", "podía", "podíamos", "podíais", "podían"],
        "subjunctive_present": ["pueda", "puedas", "pueda", "podamos", "podáis", "puedan"],
        "conditional": ["podría", "podrías", "podría", "podríamos", "podríais", "podrían"]
      },
      "imperative": {
        "tu": "puede",
        "usted": "pueda",
        "nosotros": "podamos",
        "vosotros": "poded",
        "ustedes": "puedan"
      }
    },
    {
      "inf": "decir",
      "tr": "sanoa",
      "irr": true,
      "conj": {
        "present": ["digo", "dices", "dice", "decimos", "decís", "dicen"],
        "preterite": ["dije", "dijiste", "dijo", "dijimos", "dijisteis", "dijeron"],
        "imperfect": ["decía", "decías", "decía", "decíamos", "decíais", "decían"],
        "subjunctive_present": ["diga", "digas", "diga", "digamos", "digáis", "digan"],
        "conditional": ["diría", "dirías", "diría", "diríamos", "diríais", "dirían"]
      },
      "imperative": {
        "tu": "di",
        "usted": "diga",
        "nosotros": "digamos",
        "vosotros": "decid",
        "ustedes": "digan"
      }
    },
    {
      "inf": "ver",
      "tr": "nähdä",
      "irr": true,
      "conj": {
        "present": ["veo", "ves", "ve", "vemos", "veis", "ven"],
        "preterite": ["vi", "viste", "vio", "vimos", "visteis", "vieron"],
        "imperfect": ["veía", "veías", "veía", "veíamos", "veíais", "veían"],
        "subjunctive_present": ["vea", "veas", "vea", "veamos", "veáis", "vean"],
        "conditional": ["vería", "verías", "vería", "veríamos", "veríais", "verían"]
      },
      "imperative": {
        "tu": "ve",
        "usted": "vea",
        "nosotros": "veamos",
        "vosotros": "ved",
        "ustedes": "vean"
      }
    },
    {
      "inf": "dar",
      "tr": "antaa",
      "irr": true,
      "conj": {
        "present": ["doy", "das", "da", "damos", "dais", "dan"],
        "preterite": ["di", "diste", "dio", "dimos", "disteis", "dieron"],
        "imperfect": ["daba", "dabas", "daba", "dábamos", "dabais", "daban"],
        "subjunctive_present": ["dé", "des", "dé", "demos", "deis", "den"],
        "conditional": ["daría", "darías", "daría", "daríamos", "daríais", "darían"]
      },
      "imperative": {
        "tu": "da",
        "usted": "dé",
        "nosotros": "demos",
        "vosotros": "dad",
        "ustedes": "den"
      }
    },
    {
      "inf": "saber",
      "tr": "tietää",
      "irr": true,
      "conj": {
        "present": ["sé", "sabes", "sabe", "sabemos", "sabéis", "saben"],
        "preterite": ["supe", "supiste", "supo", "supimos", "supisteis", "supieron"],
        "imperfect": ["sabía", "sabías", "sabía", "sabíamos", "sabíais", "sabían"],
        "subjunctive_present": ["sepa", "sepas", "sepa", "sepamos", "sepáis", "sepan"],
        "conditional": ["sabría", "sabrías", "sabría", "sabríamos", "sabríais", "sabrían"]
      },
      "imperative": {
        "tu": "sabe",
        "usted": "sepa",
        "nosotros": "sepamos",
        "vosotros": "sabed",
        "ustedes": "sepan"
      }
    },
    {
      "inf": "querer",
      "tr": "haluta, rakastaa",
      "irr": true,
      "conj": {
        "present": ["quiero", "quieres", "quiere", "queremos", "queréis", "quieren"],
        "preterite": ["quise", "quisiste", "quiso", "quisimos", "quisisteis", "quisieron"],
        "imperfect": ["quería", "querías", "quería", "queríamos", "queríais", "querían"],
        "subjunctive_present": ["quiera", "quieras", "quiera", "queramos", "queráis", "quieran"],
        "conditional": ["querría", "querrías", "querría", "querríamos", "querríais", "querrían"]
      },
      "imperative": {
        "tu": "quiere",
        "usted": "quiera",
        "nosotros": "queramos",
        "vosotros": "quered",
        "ustedes": "quieran"
      }
    },
    {
      "inf": "venir",
      "tr": "tulla",
      "irr": true,
      "conj": {
        "present": ["vengo", "vienes", "viene", "venimos", "venís", "vienen"],
        "preterite": ["vine", "viniste", "vino", "vinimos", "vinisteis", "vinieron"],
        "imperfect": ["venía", "venías", "venía", "veníamos", "veníais", "venían"],
        "subjunctive_present": ["venga", "vengas", "venga", "vengamos", "vengáis", "vengan"],
        "conditional": ["vendría", "vendrías", "vendría", "vendríamos", "vendríais", "vendrían"]
      },
      "imperative": {
        "tu": "ven",
        "usted": "venga",
        "nosotros": "vengamos",
        "vosotros": "venid",
        "ustedes": "vengan"
      }
    },
    {
      "inf": "poner",
      "tr": "laittaa",
      "irr": true,
      "conj": {
        "present": ["pongo", "pones", "pone", "ponemos", "ponéis", "ponen"],
        "preterite": ["puse", "pusiste", "puso", "pusimos", "pusisteis", "pusieron"],
        "imperfect": ["ponía", "ponías", "ponía", "poníamos", "poníais", "ponían"],
        "subjunctive_present": ["ponga", "pongas", "ponga", "pongamos", "pongáis", "pongan"],
        "conditional": ["pondría", "pondrías", "pondría", "pondríamos", "pondríais", "pondrían"]
      },
      "imperative": {
        "tu": "pon",
        "usted": "ponga",
        "nosotros": "pongamos",
        "vosotros": "poned",
        "ustedes": "pongan"
      }
    },
    {
      "inf": "traer",
      "tr": "tuoda",
      "irr": true,
      "conj": {
        "present": ["traigo", "traes", "trae", "traemos", "traéis", "traen"],
        "preterite": ["traje", "trajiste", "trajo", "trajimos", "trajisteis", "trajeron"],
        "imperfect": ["traía", "traías", "traía", "traíamos", "traíais", "traían"],
        "subjunctive_present": ["traiga", "traigas", "traiga", "traigamos", "traigáis", "traigan"],
        "conditional": ["traería", "traerías", "traería", "traeríamos", "traeríais", "traerían"]
      },
      "imperative": {
        "tu": "trae",
        "usted": "traiga",
        "nosotros": "traigamos",
        "vosotros": "traed",
        "ustedes": "traigan"
      }
    },
    {
      "inf": "conocer",
      "tr": "tuntea",
      "irr": true,
      "conj": {
        "present": ["conozco", "conoces", "conoce", "conocemos", "conocéis", "conocen"],
        "preterite": ["conocí", "conociste", "conoció", "conocimos", "conocisteis", "conocieron"],
        "imperfect": ["conocía", "conocías", "conocía", "conocíamos", "conocíais", "conocían"],
        "subjunctive_present": ["conozca", "conozcas", "conozca", "conozcamos", "conozcáis", "conozcan"],
        "conditional": ["conocería", "conocerías", "conocería", "conoceríamos", "conoceríais", "conocerían"]
      },
      "imperative": {
        "tu": "conoce",
        "usted": "conozca",
        "nosotros": "conozcamos",
        "vosotros": "conoced",
        "ustedes": "conozcan"
      }
    },
    {
      "inf": "salir",
      "tr": "lähteä",
      "irr": true,
      "conj": {
        "present": ["salgo", "sales", "sale", "salimos", "salís", "salen"],
        "preterite": ["salí", "saliste", "salió", "salimos", "salisteis", "salieron"],
        "imperfect": ["salía", "salías", "salía", "salíamos", "salíais", "salían"],
        "subjunctive_present": ["salga", "salgas", "salga", "salgamos", "salgáis", "salgan"],
        "conditional": ["saldría", "saldrías", "saldría", "saldríamos", "saldríais", "saldrían"]
      },
      "imperative": {
        "tu": "sal",
        "usted": "salga",
        "nosotros": "salgamos",
        "vosotros": "salid",
        "ustedes": "salgan"
      }
    },
    {
      "inf": "llevar",
      "tr": "viedä, kantaa",
      "irr": false,
      "conj": {
        "present": ["llevo", "llevas", "lleva", "llevamos", "lleváis", "llevan"],
        "preterite": ["llevé", "llevaste", "llevó", "llevamos", "llevasteis", "llevaron"],
        "imperfect": ["llevaba", "llevabas", "llevaba", "llevábamos", "llevabais", "llevaban"],
        "subjunctive_present": ["lleve", "lleves", "lleve", "llevemos", "llevéis", "lleven"],
        "conditional": ["llevaría", "llevarías", "llevaría", "llevaríamos", "llevaríais", "llevarían"]
      },
      "imperative": {
        "tu": "lleva",
        "usted": "lleve",
        "nosotros": "llevemos",
        "vosotros": "llevad",
        "ustedes": "lleven"
      }
    },
    {
      "inf": "dejar",
      "tr": "jättää",
      "irr": false,
      "conj": {
        "present": ["dejo", "dejas", "deja", "dejamos", "dejáis", "dejan"],
        "preterite": ["dejé", "dejaste", "dejó", "dejamos", "dejasteis", "dejaron"],
        "imperfect": ["dejaba", "dejabas", "dejaba", "dejábamos", "dejabais", "dejaban"],
        "subjunctive_present": ["deje", "dejes", "deje", "dejemos", "dejéis", "dejen"],
        "conditional": ["dejaría", "dejarías", "dejaría", "dejaríamos", "dejaríais", "dejarían"]
      },
      "imperative": {
        "tu": "deja",
        "usted": "deje",
        "nosotros": "dejemos",
        "vosotros": "dejad",
        "ustedes": "dejen"
      }
    },
    {
      "inf": "encontrar",
      "tr": "löytää",
      "irr": true,
      "conj": {
        "present": ["encuentro", "encuentras", "encuentra", "encontramos", "encontráis", "encuentran"],
        "preterite": ["encontré", "encontraste", "encontró", "encontramos", "encontrasteis", "encontraron"],
        "imperfect": ["encontraba", "encontrabas", "encontraba", "encontrábamos", "encontrabais", "encontraban"],
        "subjunctive_present": ["encuentre", "encuentres", "encuentre", "encontremos", "encontréis", "encuentren"],
        "conditional": ["encontraría", "encontrarías", "encontraría", "encontraríamos", "encontraríais", "encontrarían"]
      },
      "imperative": {
        "tu": "encuentra",
        "usted": "encuentre",
        "nosotros": "encontremos",
        "vosotros": "encontrad",
        "ustedes": "encuentren"
      }
    },
    {
      "inf": "pensar",
      "tr": "ajatella",
      "irr": true,
      "conj": {
        "present": ["pienso", "piensas", "piensa", "pensamos", "pensáis", "piensan"],
        "preterite": ["pensé", "pensaste", "pensó", "pensamos", "pensasteis", "pensaron"],
        "imperfect": ["pensaba", "pensabas", "pensaba", "pensábamos", "pensabais", "pensaban"],
        "subjunctive_present": ["piense", "pienses", "piense", "pensemos", "penséis", "piensen"],
        "conditional": ["pensaría", "pensarías", "pensaría", "pensaríamos", "pensaríais", "pensarían"]
      },
      "imperative": {
        "tu": "piensa",
        "usted": "piense",
        "nosotros": "pensemos",
        "vosotros": "pensad",
        "ustedes": "piensen"
      }
    },
    {
      "inf": "volver",
      "tr": "palata",
      "irr": true,
      "conj": {
        "present": ["vuelvo", "vuelves", "vuelve", "volvemos", "volvéis", "vuelven"],
        "preterite": ["volví", "volviste", "volvió", "volvimos", "volvisteis", "volvieron"],
        "imperfect": ["volvía", "volvías", "volvía", "volvíamos", "volvíais", "volvían"],
        "subjunctive_present": ["vuelva", "vuelvas", "vuelva", "volvamos", "volváis", "vuelvan"],
        "conditional": ["volvería", "volverías", "volvería", "volveríamos", "volveríais", "volverían"]
      },
      "imperative": {
        "tu": "vuelve",
        "usted": "vuelva",
        "nosotros": "volvamos",
        "vosotros": "volved",
        "ustedes": "vuelvan"
      }
    },
    {
      "inf": "empezar",
      "tr": "aloittaa",
      "irr": true,
      "conj": {
        "present": ["empiezo", "empiezas", "empieza", "empezamos", "empezáis", "empiezan"],
        "preterite": ["empecé", "empezaste", "empezó", "empezamos", "empezasteis", "empezaron"],
        "imperfect": ["empezaba", "empezabas", "empezaba", "empezábamos", "empezabais", "empezaban"],
        "subjunctive_present": ["empiece", "empieces", "empiece", "empecemos", "empecéis", "empiecen"],
        "conditional": ["empezaría", "empezarías", "empezaría", "empezaríamos", "empezaríais", "empezarían"]
      },
      "imperative": {
        "tu": "empieza",
        "usted": "empiece",
        "nosotros": "empecemos",
        "vosotros": "empezad",
        "ustedes": "empiecen"
      }
    },
    {
      "inf": "entender",
      "tr": "ymmärtää",
      "irr": true,
      "conj": {
        "present": ["entiendo", "entiendes", "entiende", "entendemos", "entendéis", "entienden"],
        "preterite": ["entendí", "entendiste", "entendió", "entendimos", "entendisteis", "entendieron"],
        "imperfect": ["entendía", "entendías", "entendía", "entendíamos", "entendíais", "entendían"],
        "subjunctive_present": ["entienda", "entiendas", "entienda", "entendamos", "entendáis", "entiendan"],
        "conditional": ["entendería", "entenderías", "entendería", "entenderíamos", "entenderíais", "entenderían"]
      },
      "imperative": {
        "tu": "entiende",
        "usted": "entienda",
        "nosotros": "entendamos",
        "vosotros": "entended",
        "ustedes": "entiendan"
      }
    },
    {
      "inf": "pedir",
      "tr": "pyytää",
      "irr": true,
      "conj": {
        "present": ["pido", "pides", "pide", "pedimos", "pedís", "piden"],
        "preterite": ["pedí", "pediste", "pidió", "pedimos", "pedisteis", "pidieron"],
        "imperfect": ["pedía", "pedías", "pedía", "pedíamos", "pedíais", "pedían"],
        "subjunctive_present": ["pida", "pidas", "pida", "pidamos", "pidáis", "pidan"],
        "conditional": ["pediría", "pedirías", "pediría", "pediríamos", "pediríais", "pedirían"]
      },
      "imperative": {
        "tu": "pide",
        "usted": "pida",
        "nosotros": "pidamos",
        "vosotros": "pedid",
        "ustedes": "pidan"
      }
    },
    {
      "inf": "sentir",
      "tr": "tuntea",
      "irr": true,
      "conj": {
        "present": ["siento", "sientes", "siente", "sentimos", "sentís", "sienten"],
        "preterite": ["sentí", "sentiste", "sintió", "sentimos", "sentisteis", "sintieron"],
        "imperfect": ["sentía", "sentías", "sentía", "sentíamos", "sentíais", "sentían"],
        "subjunctive_present": ["sienta", "sientas", "sienta", "sintamos", "sintáis", "sientan"],
        "conditional": ["sentiría", "sentirías", "sentiría", "sentiríamos", "sentiríais", "sentirían"]
      },
      "imperative": {
        "tu": "siente",
        "usted": "sienta",
        "nosotros": "sintamos",
        "vosotros": "sentid",
        "ustedes": "sientan"
      }
    },
    {
      "inf": "dormir",
      "tr": "nukkua",
      "irr": true,
      "conj": {
        "present": ["duermo", "duermes", "duerme", "dormimos", "dormís", "duermen"],
        "preterite": ["dormí", "dormiste", "durmió", "dormimos", "dormisteis", "durmieron"],
        "imperfect": ["dormía", "dormías", "dormía", "dormíamos", "dormíais", "dormían"],
        "subjunctive_present": ["duerma", "duermas", "duerma", "durmamos", "durmáis", "duerman"],
        "conditional": ["dormiría", "dormirías", "dormiría", "dormiríamos", "dormiríais", "dormirían"]
      },
      "imperative": {
        "tu": "duerme",
        "usted": "duerma",
        "nosotros": "durmamos",
        "vosotros": "dormid",
        "ustedes": "duerman"
      }
    },
    {
      "inf": "jugar",
      "tr": "pelata",
      "irr": true,
      "conj": {
        "present": ["juego", "juegas", "juega", "jugamos", "jugáis", "juegan"],
        "preterite": ["jugué", "jugaste", "jugó", "jugamos", "jugasteis", "jugaron"],
        "imperfect": ["jugaba", "jugabas", "jugaba", "jugábamos", "jugabais", "jugaban"],
        "subjunctive_present": ["juegue", "juegues", "juegue", "juguemos", "juguéis", "jueguen"],
        "conditional": ["jugaría", "jugarías", "jugaría", "jugaríamos", "jugaríais", "jugarían"]
      },
      "imperative": {
        "tu": "juega",
        "usted": "juegue",
        "nosotros": "juguemos",
        "vosotros": "jugad",
        "ustedes": "jueguen"
      }
    },
    {
      "inf": "seguir",
      "tr": "seurata, jatkaa",
      "irr": true,
      "conj": {
        "present": ["sigo", "sigues", "sigue", "seguimos", "seguís", "siguen"],
        "preterite": ["seguí", "seguiste", "siguió", "seguimos", "seguisteis", "siguieron"],
        "imperfect": ["seguía", "seguías", "seguía", "seguíamos", "seguíais", "seguían"],
        "subjunctive_present": ["siga", "sigas", "siga", "sigamos", "sigáis", "sigan"],
        "conditional": ["seguiría", "seguirías", "seguiría", "seguiríamos", "seguiríais", "seguirían"]
      },
      "imperative": {
        "tu": "sigue",
        "usted": "siga",
        "nosotros": "sigamos",
        "vosotros": "seguid",
        "ustedes": "sigan"
      }
    },
    {
      "inf": "leer",
      "tr": "lukea",
      "irr": true,
      "conj": {
        "present": ["leo", "lees", "lee", "leemos", "leéis", "leen"],
        "preterite": ["leí", "leíste", "leyó", "leímos", "leísteis", "leyeron"],
        "imperfect": ["leía", "leías", "leía", "leíamos", "leíais", "leían"],
        "subjunctive_present": ["lea", "leas", "lea", "leamos", "leáis", "lean"],
        "conditional": ["leería", "leerías", "leería", "leeríamos", "leeríais", "leerían"]
      },
      "imperative": {
        "tu": "lee",
        "usted": "lea",
        "nosotros": "leamos",
        "vosotros": "leed",
        "ustedes": "lean"
      }
    },
    {
      "inf": "oír",
      "tr": "kuulla",
      "irr": true,
      "conj": {
        "present": ["oigo", "oyes", "oye", "oímos", "oís", "oyen"],
        "preterite": ["oí", "oíste", "oyó", "oímos", "oísteis", "oyeron"],
        "imperfect": ["oía", "oías", "oía", "oíamos", "oíais", "oían"],
        "subjunctive_present": ["oiga", "oigas", "oiga", "oigamos", "oigáis", "oigan"],
        "conditional": ["oiría", "oirías", "oiría", "oiríamos", "oiríais", "oirían"]
      },
      "imperative": {
        "tu": "oye",
        "usted": "oiga",
        "nosotros": "oigamos",
        "vosotros": "oíd",
        "ustedes": "oigan"
      }
    },
    {
      "inf": "vivir",
      "tr": "asua",
      "irr": false,
      "conj": {
        "present": ["vivo", "vives", "vive", "vivimos", "vivís", "viven"],
        "preterite": ["viví", "viviste", "vivió", "vivimos", "vivisteis", "vivieron"],
        "imperfect": ["vivía", "vivías", "vivía", "vivíamos", "vivíais", "vivían"],
        "subjunctive_present": ["viva", "vivas", "viva", "vivamos", "viváis", "vivan"],
        "conditional": ["viviría", "vivirías", "viviría", "viviríamos", "viviríais", "vivirían"]
      },
      "imperative": {
        "tu": "vive",
        "usted": "viva",
        "nosotros": "vivamos",
        "vosotros": "vivid",
        "ustedes": "vivan"
      }
    },
    {
      "inf": "hablar",
      "tr": "puhua",
      "irr": false,
      "conj": {
        "present": ["hablo", "hablas", "habla", "hablamos", "habláis", "hablan"],
        "preterite": ["hablé", "hablaste", "habló", "hablamos", "hablasteis", "hablaron"],
        "imperfect": ["hablaba", "hablabas", "hablaba", "hablábamos", "hablabais", "hablaban"],
        "subjunctive_present": ["hable", "hables", "hable", "hablemos", "habléis", "hablen"],
        "conditional": ["hablaría", "hablarías", "hablaría", "hablaríamos", "hablaríais", "hablarían"]
      },
      "imperative": {
        "tu": "habla",
        "usted": "hable",
        "nosotros": "hablemos",
        "vosotros": "hablad",
        "ustedes": "hablen"
      }
    },
    {
      "inf": "comer",
      "tr": "syödä",
      "irr": false,
      "conj": {
        "present": ["como", "comes", "come", "comemos", "coméis", "comen"],
        "preterite": ["comí", "comiste", "comió", "comimos", "comisteis", "comieron"],
        "imperfect": ["comía", "comías", "comía", "comíamos", "comíais", "comían"],
        "subjunctive_present": ["coma", "comas", "coma", "comamos", "comáis", "coman"],
        "conditional": ["comería", "comerías", "comería", "comeríamos", "comeríais", "comerían"]
      },
      "imperative": {
        "tu": "come",
        "usted": "coma",
        "nosotros": "comamos",
        "vosotros": "comed",
        "ustedes": "coman"
      }
    },
    {
      "inf": "estudiar",
      "tr": "opiskella",
      "irr": false,
      "conj": {
        "present": ["estudio", "estudias", "estudia", "estudiamos", "estudiáis", "estudian"],
        "preterite": ["estudié", "estudiaste", "estudió", "estudiamos", "estudiasteis", "estudiaron"],
        "imperfect": ["estudiaba", "estudiabas", "estudiaba", "estudiábamos", "estudiabais", "estudiaban"],
        "subjunctive_present": ["estudie", "estudies", "estudie", "estudiemos", "estudiéis", "estudien"],
        "conditional": ["estudiaría", "estudiarías", "estudiaría", "estudiaríamos", "estudiaríais", "estudiarían"]
      },
      "imperative": {
        "tu": "estudia",
        "usted": "estudie",
        "nosotros": "estudiemos",
        "vosotros": "estudiad",
        "ustedes": "estudien"
      }
    },
    {
      "inf": "trabajar",
      "tr": "työskennellä",
      "irr": false,
      "conj": {
        "present": ["trabajo", "trabajas", "trabaja", "trabajamos", "trabajáis", "trabajan"],
        "preterite": ["trabajé", "trabajaste", "trabajó", "trabajamos", "trabajasteis", "trabajaron"],
        "imperfect": ["trabajaba", "trabajabas", "trabajaba", "trabajábamos", "trabajabais", "trabajaban"],
        "subjunctive_present": ["trabaje", "trabajes", "trabaje", "trabajemos", "trabajéis", "trabajen"],
        "conditional": ["trabajaría", "trabajarías", "trabajaría", "trabajaríamos", "trabajaríais", "trabajarían"]
      },
      "imperative": {
        "tu": "trabaja",
        "usted": "trabaje",
        "nosotros": "trabajemos",
        "vosotros": "trabajad",
        "ustedes": "trabajen"
      }
    },
    {
      "inf": "escribir",
      "tr": "kirjoittaa",
      "irr": false,
      "conj": {
        "present": ["escribo", "escribes", "escribe", "escribimos", "escribís", "escriben"],
        "preterite": ["escribí", "escribiste", "escribió", "escribimos", "escribisteis", "escribieron"],
        "imperfect": ["escribía", "escribías", "escribía", "escribíamos", "escribíais", "escribían"],
        "subjunctive_present": ["escriba", "escribas", "escriba", "escribamos", "escribáis", "escriban"],
        "conditional": ["escribiría", "escribirías", "escribiría", "escribiríamos", "escribiríais", "escribirían"]
      },
      "imperative": {
        "tu": "escribe",
        "usted": "escriba",
        "nosotros": "escribamos",
        "vosotros": "escribid",
        "ustedes": "escriban"
      }
    },
    {
      "inf": "gustar",
      "tr": "miellyttää",
      "irr": false,
      "conj": {
        "present": ["gusto", "gustas", "gusta", "gustamos", "gustáis", "gustan"],
        "preterite": ["gusté", "gustaste", "gustó", "gustamos", "gustasteis", "gustaron"],
        "imperfect": ["gustaba", "gustabas", "gustaba", "gustábamos", "gustabais", "gustaban"],
        "subjunctive_present": ["guste", "gustes", "guste", "gustemos", "gustéis", "gusten"],
        "conditional": ["gustaría", "gustarías", "gustaría", "gustaríamos", "gustaríais", "gustarían"]
      },
      "imperative": {
        "tu": "gusta",
        "usted": "guste",
        "nosotros": "gustemos",
        "vosotros": "gustad",
        "ustedes": "gusten"
      }
    },
    {
      "inf": "aprender",
      "tr": "oppia",
      "irr": false,
      "conj": {
        "present": ["aprendo", "aprendes", "aprende", "aprendemos", "aprendéis", "aprenden"],
        "preterite": ["aprendí", "aprendiste", "aprendió", "aprendimos", "aprendisteis", "aprendieron"],
        "imperfect": ["aprendía", "aprendías", "aprendía", "aprendíamos", "aprendíais", "aprendían"],
        "subjunctive_present": ["aprenda", "aprendas", "aprenda", "aprendamos", "aprendáis", "aprendan"],
        "conditional": ["aprendería", "aprenderías", "aprendería", "aprenderíamos", "aprenderíais", "aprenderían"]
      },
      "imperative": {
        "tu": "aprende",
        "usted": "aprenda",
        "nosotros": "aprendamos",
        "vosotros": "aprended",
        "ustedes": "aprendan"
      }
    },
    {
      "inf": "creer",
      "tr": "uskoa, luulla",
      "irr": true,
      "conj": {
        "present": ["creo", "crees", "cree", "creemos", "creéis", "creen"],
        "preterite": ["creí", "creíste", "creyó", "creímos", "creísteis", "creyeron"],
        "imperfect": ["creía", "creías", "creía", "creíamos", "creíais", "creían"],
        "subjunctive_present": ["crea", "creas", "crea", "creamos", "creáis", "crean"],
        "conditional": ["creería", "creerías", "creería", "creeríamos", "creeríais", "creerían"]
      },
      "imperative": {
        "tu": "cree",
        "usted": "crea",
        "nosotros": "creamos",
        "vosotros": "creed",
        "ustedes": "crean"
      }
    }
  ]
}
